{
  "version": 1,
  "presetId": "shifter-snakeskin",
  "title": "Shifter - Snakeskin",
  "stimsArtifactId": "stims-capture--milkdrop--preset--shifter-snakeskin--20260529232701",
  "projectmImagePath": "/Users/kanav/Dev/stims/tests/fixtures/milkdrop/projectm-reference/shifter-snakeskin.png",
  "requiredBackend": "webgl",
  "actualBackend": "webgpu",
  "sourceFamily": "bundled",
  "strata": [
    "bundled",
    "cream-of-the-crop"
  ],
  "toleranceProfile": "loose",
  "threshold": 32,
  "failThreshold": 0.05,
  "metrics": {
    "mismatchRatio": null
  },
  "status": "backend-mismatch",
  "error": "Certified preset requires WEBGL. Latest Stims capture used WEBGPU."
}
